vwo_provider
