Metadata-Version: 2.1
Name: vwo-openfeature-provider-python
Version: 1.1.0
Summary: VWO OpenFeature Provider Python
Home-page: https://github.com/wingify/vwo-openfeature-provider-python
Author: VWO
Author-email: dev@wingify.com
License: Apache License 2.0
Classifier: Development Status :: 5 - Production/Stable
Classifier: Environment :: Web Environment
Classifier: Intended Audience :: Developers
Classifier: License :: OSI Approved :: Apache Software License
Classifier: Operating System :: OS Independent
Classifier: Programming Language :: Python
Classifier: Programming Language :: Python :: 3.9
Classifier: Programming Language :: Python :: 3.10
Classifier: Programming Language :: Python :: 3.11
License-File: LICENSE
License-File: NOTICE
Requires-Dist: openfeature-sdk==0.7.1
